{
  "id": "ba3824f1-0a7c-4b56-9cb0-ad0da4e01e12",
  "agentId": "agent-5",
  "rationale": "Pattern \"coder.read-file → coder.write-file\" observed 7 times (85% success rate) across 10 traces (avg quality 75.0%). Suggest pre-loading these tools or adjusting tool_order preference.",
  "delta": {
    "tools": {
      "preferred_sequence": [
        "coder.read-file",
        "coder.write-file"
      ],
      "preload": [
        "coder.read-file",
        "coder.write-file"
      ]
    },
    "learning": {
      "observed_pattern_id": "7872ebf7-f352-4a",
      "pattern_success_rate": 0.85,
      "pattern_occurrence_count": 7
    }
  },
  "traceQuality": 0.75,
  "traceCount": 10,
  "status": "pending",
  "createdAt": "2026-04-18T19:47:21.805Z",
  "updatedAt": "2026-04-18T19:47:21.805Z"
}